xtext/__init__.py
xtext-1.0.10.dist-info/METADATA
xtext-1.0.10.dist-info/WHEEL
xtext-1.0.10.dist-info/licenses/LICENSE
xtext-1.0.10.dist-info/RECORD
